browser2requests/README.MD
browser2requests/__init__.py
browser2requests/requirements.txt
browser2requests/thirdparty.json
browser2requests-0.10.dist-info/LICENSE.rst
browser2requests-0.10.dist-info/METADATA
browser2requests-0.10.dist-info/WHEEL
browser2requests-0.10.dist-info/top_level.txt
browser2requests-0.10.dist-info/RECORD
