Metadata-Version: 2.1
Name: browser2requests
Version: 0.10
Summary: A class for capturing network requests in a browser and converting them to a pandas DataFrame - Windows only
Home-page: https://github.com/hansalemaos/browser2requests
Author: Johannes Fischer
Author-email: aulasparticularesdealemaosp@gmail.com
License: MIT
Keywords: requests,chrome
Classifier: Development Status :: 4 - Beta
Classifier: Programming Language :: Python :: 3 :: Only
Classifier: Programming Language :: Python :: 3.10
Classifier: Topic :: Software Development :: Libraries :: Python Modules
Classifier: Topic :: Utilities
License-File: LICENSE.rst
Requires-Dist: flatten-any-dict-iterable-or-whatsoever
Requires-Dist: pandas
Requires-Dist: pychrome
